tests/__init__.py
tests/test_cam_projections.py
tests/test_detection2d.py
tests/test_flowutils.py
tests/test_imutils.py
tests/test_imvis.py
tests/test_pyutils.py
vito/__init__.py
vito/cam_projections.py
vito/colormaps.py
vito/detection2d.py
vito/flowutils.py
vito/imutils.py
vito/imvis.py
vito/pyutils.py
vito/version.py
vito-1.6.1.dist-info/LICENSE
vito-1.6.1.dist-info/METADATA
vito-1.6.1.dist-info/WHEEL
vito-1.6.1.dist-info/top_level.txt
vito-1.6.1.dist-info/RECORD
