Metadata-Version: 2.1
Name: vito
Version: 1.6.1
Summary: Lightweight utility package for common computer vision tasks.
Home-page: https://github.com/snototter/vito
Author: snototter
Author-email: snototter@users.noreply.github.com
Classifier: Programming Language :: Python :: 3
Classifier: License :: OSI Approved :: MIT License
Classifier: Operating System :: OS Independent
Requires-Python: >=3.6
License-File: LICENSE
Requires-Dist: numpy
Requires-Dist: Pillow >=5.0.0
